pygeodesic/version.py
pygeodesic/geodesic.cpp
pygeodesic/__init__.py
pygeodesic/geodesic.pyx
pygeodesic/geodesic.cpython-311-darwin.so
pygeodesic/geodesic_kirsanov/geodesic_algorithm_base.h
pygeodesic/geodesic_kirsanov/geodesic_algorithm_dijkstra_alternative.h
pygeodesic/geodesic_kirsanov/geodesic_matlab_api.h
pygeodesic/geodesic_kirsanov/geodesic_algorithm_graph_base.h
pygeodesic/geodesic_kirsanov/geodesic_mesh.h
pygeodesic/geodesic_kirsanov/geodesic_algorithm_exact_elements.h
pygeodesic/geodesic_kirsanov/geodesic_algorithm_exact.h
pygeodesic/geodesic_kirsanov/geodesic_mesh_elements.h
pygeodesic/geodesic_kirsanov/geodesic_memory.h
pygeodesic/geodesic_kirsanov/example1.cpp
pygeodesic/geodesic_kirsanov/example0.cpp
pygeodesic/geodesic_kirsanov/geodesic_constants_and_simple_functions.h
pygeodesic/geodesic_kirsanov/geodesic_algorithm_dijkstra.h
pygeodesic/geodesic_kirsanov/geodesic_algorithm_subdivision.h
pygeodesic/geodesic_kirsanov/geodesic_matlab_api.cpp
pygeodesic-0.1.11.dist-info/RECORD
pygeodesic-0.1.11.dist-info/LICENSE
pygeodesic-0.1.11.dist-info/WHEEL
pygeodesic-0.1.11.dist-info/top_level.txt
pygeodesic-0.1.11.dist-info/METADATA
