Metadata-Version: 2.1
Name: pygeodesic
Version: 0.1.11
Summary: Python library for calculating geodesic distance on triangular based surface meshes
Home-page: https://github.com/mhogg/pygeodesic
Download-URL: https://github.com/mhogg/pygeodesic/releases
Author: Michael Hogg
Author-email: michael.christopher.hogg@gmail.com
License: MIT license
Keywords: geodesic,distance,path,triangle,mesh,python,cython
Classifier: Development Status :: 4 - Beta
Classifier: License :: OSI Approved :: MIT License
Classifier: Operating System :: OS Independent
Classifier: Programming Language :: Python
Classifier: Programming Language :: Cython
Classifier: Programming Language :: C++
Classifier: Programming Language :: Python :: 3
Classifier: Programming Language :: Python :: 3.9
Classifier: Programming Language :: Python :: 3.10
Classifier: Programming Language :: Python :: 3.11
Classifier: Programming Language :: Python :: 3.12
Classifier: Programming Language :: Python :: 3.13
Requires-Python: >=3.9
License-File: LICENSE
Requires-Dist: numpy<3,>=2
